README.md
setup.cfg
setup.py
gb_loop/Binomialdistribution.py
gb_loop/Gaussiandistribution.py
gb_loop/Generaldistribution.py
gb_loop/__init__.py
gb_loop.egg-info/PKG-INFO
gb_loop.egg-info/SOURCES.txt
gb_loop.egg-info/dependency_links.txt
gb_loop.egg-info/not-zip-safe
gb_loop.egg-info/top_level.txt